clarity/__init__.py
clarity/_version.py
clarity/data/HOA_tools_cec2.py
clarity/data/__init__.py
clarity/data/demo_data.py
clarity/data/scene_builder_cec2.py
clarity/data/scene_renderer_cec1.py
clarity/data/scene_renderer_cec2.py
clarity/data/utils.py
clarity/data/params/speech_weight.mat
clarity/dataset/cec1_dataset.py
clarity/engine/__init__.py
clarity/engine/losses.py
clarity/engine/system.py
clarity/enhancer/__init__.py
clarity/enhancer/compressor.py
clarity/enhancer/nalr.py
clarity/enhancer/dnn/__init__.py
clarity/enhancer/dnn/mc_conv_tasnet.py
clarity/enhancer/dsp/__init__.py
clarity/enhancer/dsp/filter.py
clarity/enhancer/gha/__init__.py
clarity/enhancer/gha/gainrule_camfit.py
clarity/enhancer/gha/gha_interface.py
clarity/enhancer/gha/gha_utils.py
clarity/enhancer/gha/cfg_files/prerelease_combination3_smooth_template.cfg
clarity/enhancer/gha/cfg_files/prerelease_combination4_smooth_template.cfg
clarity/enhancer/multiband_compressor/__init__.py
clarity/enhancer/multiband_compressor/compressor_qmul.py
clarity/enhancer/multiband_compressor/crossover.py
clarity/enhancer/multiband_compressor/multiband_compressor.py
clarity/evaluator/__init__.py
clarity/evaluator/haaqi/__init__.py
clarity/evaluator/haaqi/haaqi.py
clarity/evaluator/haspi/__init__.py
clarity/evaluator/haspi/eb.py
clarity/evaluator/haspi/ebm.py
clarity/evaluator/haspi/haspi.py
clarity/evaluator/haspi/ip.py
clarity/evaluator/hasqi/__init__.py
clarity/evaluator/hasqi/hasqi.py
clarity/evaluator/mbstoi/__init__.py
clarity/evaluator/mbstoi/mbstoi.py
clarity/evaluator/mbstoi/mbstoi_utils.py
clarity/evaluator/mbstoi/parameters.yaml
clarity/evaluator/msbg/__init__.py
clarity/evaluator/msbg/cochlea.py
clarity/evaluator/msbg/msbg.py
clarity/evaluator/msbg/msbg_utils.py
clarity/evaluator/msbg/smearing.py
clarity/evaluator/msbg/msbg_hparams/GT4FBank_Brd1.5E_Spaced1.1E_44100Fs.json
clarity/evaluator/msbg/msbg_hparams/GT4FBank_Brd2.0E_Spaced1.5E_44100Fs.json
pyclarity-0.8.0.dist-info/licenses/LICENSE
pyclarity-0.8.0.dist-info/METADATA
pyclarity-0.8.0.dist-info/WHEEL
pyclarity-0.8.0.dist-info/top_level.txt
pyclarity-0.8.0.dist-info/RECORD
