Metadata-Version: 2.4
Name: pyclarity
Version: 0.8.0
Summary: Tools for the Clarity Challenge
Author-email: The PyClarity Team <claritychallengecontact@gmail.com>
License: MIT
Project-URL: Source, https://github.com/claritychallenge/clarity
Project-URL: Bug_Tracker, https://github.com/claritychallenge/clarity/issues
Project-URL: Documentation, https://claritychallenge.github.io/clarity_CC_doc
Keywords: hearing,signal processing,clarity challenge
Classifier: Intended Audience :: Developers
Classifier: Intended Audience :: Education
Classifier: Intended Audience :: Science/Research
Classifier: License :: OSI Approved :: MIT License
Classifier: Operating System :: OS Independent
Classifier: Programming Language :: Python :: 3
Classifier: Natural Language :: English
Requires-Python: >=3.9
License-File: LICENSE
Requires-Dist: audioread>=2.1.9
Requires-Dist: gdown
Requires-Dist: hydra-core>=1.1.1
Requires-Dist: hydra-submitit-launcher>=1.1.6
Requires-Dist: importlib-metadata
Requires-Dist: librosa>=0.8.1
Requires-Dist: matplotlib
Requires-Dist: numba>=0.60
Requires-Dist: numpy>=2
Requires-Dist: omegaconf>=2.1.1
Requires-Dist: pandas>=2.2.2
Requires-Dist: pyflac
Requires-Dist: pylint>=3.2.7
Requires-Dist: pylint-pytest>=1.1.7
Requires-Dist: pyloudnorm>=0.1.0
Requires-Dist: pystoi
Requires-Dist: pytorch-lightning
Requires-Dist: resampy
Requires-Dist: safetensors>=0.4.3
Requires-Dist: scikit-learn>=1.0.2
Requires-Dist: scipy>=1.7.3
Requires-Dist: SoundFile>=0.10.3.post1
Requires-Dist: soxr>=0.4
Requires-Dist: torch>=2
Requires-Dist: torchaudio
Requires-Dist: tqdm>=4.62.3
Requires-Dist: typing_extensions
Provides-Extra: tests
Requires-Dist: coverage; extra == "tests"
Requires-Dist: isort; extra == "tests"
Requires-Dist: flake8; extra == "tests"
Requires-Dist: flake8-print; extra == "tests"
Requires-Dist: Flake8-pyproject; extra == "tests"
Requires-Dist: mypy; extra == "tests"
Requires-Dist: pre-commit; extra == "tests"
Requires-Dist: py; extra == "tests"
Requires-Dist: py-cpuinfo; extra == "tests"
Requires-Dist: pytest; extra == "tests"
Requires-Dist: pytest-cov; extra == "tests"
Requires-Dist: pytest-mock; extra == "tests"
Requires-Dist: pytest-mpl; extra == "tests"
Requires-Dist: pytest-regtest; extra == "tests"
Requires-Dist: pytest-skip-slow; extra == "tests"
Requires-Dist: pytest-xdist; extra == "tests"
Requires-Dist: yamllint; extra == "tests"
Provides-Extra: docs
Requires-Dist: sphinx; extra == "docs"
Requires-Dist: myst_parser; extra == "docs"
Requires-Dist: pydata_sphinx_theme; extra == "docs"
Requires-Dist: sphinx_markdown_tables; extra == "docs"
Requires-Dist: sphinx_rtd_theme; extra == "docs"
Requires-Dist: sphinxcontrib-mermaid; extra == "docs"
Requires-Dist: sphinxcontrib-napoleon; extra == "docs"
Provides-Extra: dev
Requires-Dist: black; extra == "dev"
Requires-Dist: pre-commit; extra == "dev"
Requires-Dist: pycodestyle; extra == "dev"
Requires-Dist: pylint; extra == "dev"
Requires-Dist: pylint-pytest; extra == "dev"
Requires-Dist: yamllint; extra == "dev"
Provides-Extra: pypi
Requires-Dist: build; extra == "pypi"
Requires-Dist: wheel; extra == "pypi"
Requires-Dist: setuptools_scm[toml]; extra == "pypi"
Dynamic: license-file
